owid/repack/__init__.py
owid_repack-0.1.6.dist-info/METADATA
owid_repack-0.1.6.dist-info/WHEEL
owid_repack-0.1.6.dist-info/licenses/LICENSE
owid_repack-0.1.6.dist-info/RECORD
