Metadata-Version: 2.4
Name: owid-repack
Version: 0.1.6
Summary: Pack Pandas data frames into smaller, more memory-efficient data types.
Author-email: Our World in Data <tech@ourworldindata.org>
License-Expression: MIT
License-File: LICENSE
Requires-Python: >=3.10
Requires-Dist: numpy>=1.24.0
Requires-Dist: pandas>=2.2.3
Requires-Dist: pyarrow>=18.0.0
